gguf_py/__init__.py
gguf_py-0.0.7.dist-info/entry_points.txt
gguf_py-0.0.7.dist-info/LICENSE
gguf_py-0.0.7.dist-info/WHEEL
gguf_py-0.0.7.dist-info/METADATA
gguf_py-0.0.7.dist-info/RECORD
