Metadata-Version: 2.1
Name: gguf-py
Version: 0.0.7
Summary: gguf python package
Author-email: gguf <info@gguf.us>
Classifier: License :: OSI Approved :: MIT License
Requires-Dist: gguf-connector >=1.8.6
Requires-Dist: pig-gguf >=0.0.5
Project-URL: Repository, https://github.com/gguf-org/pig
